smc_monitoring/__init__.py
smc_monitoring/wsocket.py
smc_monitoring/models/__init__.py
smc_monitoring/models/calendar.py
smc_monitoring/models/constants.py
smc_monitoring/models/filters.py
smc_monitoring/models/formats.py
smc_monitoring/models/formatters.py
smc_monitoring/models/query.py
smc_monitoring/models/values.py
smc_monitoring/monitors/__init__.py
smc_monitoring/monitors/alerts.py
smc_monitoring/monitors/blacklist.py
smc_monitoring/monitors/block_list.py
smc_monitoring/monitors/connections.py
smc_monitoring/monitors/logs.py
smc_monitoring/monitors/neighbors.py
smc_monitoring/monitors/routes.py
smc_monitoring/monitors/sslvpn.py
smc_monitoring/monitors/users.py
smc_monitoring/monitors/vpns.py
smc_monitoring/pubsub/__init__.py
smc_monitoring/pubsub/subscribers.py
tests/__init__.py
tests/docker_smc_bootstrap.py
tests/test_filters.py
tests/test_queries.py
fp_ngfw_smc_python_monitoring-1.5.6.dist-info/METADATA
fp_ngfw_smc_python_monitoring-1.5.6.dist-info/WHEEL
fp_ngfw_smc_python_monitoring-1.5.6.dist-info/top_level.txt
fp_ngfw_smc_python_monitoring-1.5.6.dist-info/RECORD
