Metadata-Version: 2.4
Name: fp-NGFW-SMC-python-monitoring
Version: 1.5.6
Summary: Forcepoint NGFW Management Center Monitoring
Home-page: https://github.com/Forcepoint/fp-NGFW-SMC-python
Author: Forcepoint
Author-email: PSIRT@forcepoint.com
License: Apache License
Classifier: Development Status :: 5 - Production/Stable
Classifier: Programming Language :: Python
Classifier: Programming Language :: Python :: 3.5
Classifier: Programming Language :: Python :: 3.6
Classifier: Programming Language :: Python :: 3
Classifier: License :: OSI Approved :: Apache Software License
Requires-Dist: fp_NGFW_SMC_python>=1.0.19
Requires-Dist: websocket-client>=1.5.0
Dynamic: author
Dynamic: author-email
Dynamic: classifier
Dynamic: description
Dynamic: home-page
Dynamic: license
Dynamic: requires-dist
Dynamic: summary
